pytransaln/__init__.py
pytransaln/align.py
pytransaln/frameshifts.py
pytransaln/pytransaln.py
pytransaln/stats.py
pytransaln/testmodule.py
pytransaln/translate.py
pytransaln-0.2.1.dist-info/LICENSE
pytransaln-0.2.1.dist-info/METADATA
pytransaln-0.2.1.dist-info/WHEEL
pytransaln-0.2.1.dist-info/entry_points.txt
pytransaln-0.2.1.dist-info/top_level.txt
pytransaln-0.2.1.dist-info/RECORD
