Metadata-Version: 2.1
Name: pytransaln
Version: 0.2.1
Summary: Translation-guided nucleotide alignment for coding sequences
Author-email: Brandon Seah <brandon.seah@thuenen.de>
License: 
Project-URL: Homepage, https://github.com/monagrland/pytransaln
Project-URL: Repository, https://github.com/monagrland/pytransaln.git
License-File: LICENSE
Requires-Dist: biopython <2,>=1.80
Requires-Dist: pandas <3,>=1.3
Requires-Dist: matplotlib <4,>=3.6
Requires-Dist: pyhmmer ==0.10
